llamaindex_test/__init__.py
llamaindex_test/agent_deployments/__init__.py
llamaindex_test/agent_deployments/client.py
llamaindex_test/agent_deployments/raw_client.py
llamaindex_test/alpha/__init__.py
llamaindex_test/alpha/client.py
llamaindex_test/alpha/raw_client.py
llamaindex_test/api_keys/__init__.py
llamaindex_test/api_keys/client.py
llamaindex_test/api_keys/raw_client.py
llamaindex_test/auth/__init__.py
llamaindex_test/auth/client.py
llamaindex_test/auth/raw_client.py
llamaindex_test/beta/__init__.py
llamaindex_test/beta/client.py
llamaindex_test/beta/raw_client.py
llamaindex_test/billing/__init__.py
llamaindex_test/billing/client.py
llamaindex_test/billing/raw_client.py
llamaindex_test/billing/types/__init__.py
llamaindex_test/billing/types/billing_create_intent_and_session_request_plan_name.py
llamaindex_test/classifier/__init__.py
llamaindex_test/classifier/client.py
llamaindex_test/classifier/raw_client.py
llamaindex_test/client.py
llamaindex_test/core/__init__.py
llamaindex_test/core/api_error.py
llamaindex_test/core/client_wrapper.py
llamaindex_test/core/datetime_utils.py
llamaindex_test/core/file.py
llamaindex_test/core/force_multipart.py
llamaindex_test/core/http_client.py
llamaindex_test/core/http_response.py
llamaindex_test/core/http_sse/__init__.py
llamaindex_test/core/http_sse/_api.py
llamaindex_test/core/http_sse/_decoders.py
llamaindex_test/core/http_sse/_exceptions.py
llamaindex_test/core/http_sse/_models.py
llamaindex_test/core/jsonable_encoder.py
llamaindex_test/core/pydantic_utilities.py
llamaindex_test/core/query_encoder.py
llamaindex_test/core/remove_none_from_dict.py
llamaindex_test/core/request_options.py
llamaindex_test/core/serialization.py
llamaindex_test/core/unchecked_base_model.py
llamaindex_test/data_sinks/__init__.py
llamaindex_test/data_sinks/client.py
llamaindex_test/data_sinks/raw_client.py
llamaindex_test/data_sinks/types/__init__.py
llamaindex_test/data_sinks/types/data_sink_update_component.py
llamaindex_cloud_fern_test-0.0.3.dist-info/METADATA
llamaindex_cloud_fern_test-0.0.3.dist-info/WHEEL
llamaindex_cloud_fern_test-0.0.3.dist-info/RECORD
